{
  "_description": "Best data source for each dataset based on number of models",
  "_generated": "Based on comparison of TinyBenchmarks pickle files vs Aggregated parquet files",
  
  "datasets": {
    "ARC Challenge": {
      "source_type": "tinybenchmarks",
      "source_file": "lb.pickle",
      "pickle_keys": ["harness_arc_challenge_25"],
      "models": 395,
      "items": 1212
    },
    "Alpaca v2": {
      "source_type": "tinybenchmarks",
      "source_file": "alpaca_v2.pickle",
      "pickle_keys": ["alpaca_v2"],
      "models": 100,
      "items": 805
    },
    "GSM": {
      "source_type": "tinybenchmarks",
      "source_file": "helm_lite.pickle",
      "pickle_keys": ["gsm:"],
      "models": 30,
      "items": 1000
    },
    "GSM8K": {
      "source_type": "tinybenchmarks",
      "source_file": "lb.pickle",
      "pickle_keys": ["harness_gsm8k_5"],
      "models": 395,
      "items": 1359
    },
    "HellaSwag": {
      "source_type": "tinybenchmarks",
      "source_file": "lb.pickle",
      "pickle_keys": ["harness_hellaswag_10"],
      "models": 395,
      "items": 10082
    },
    "ICL Templates": {
      "source_type": "tinybenchmarks",
      "source_file": "icl_templates.pickle",
      "pickle_keys": ["templates"],
      "models": 240,
      "items": 750
    },
    "LegalBench": {
      "source_type": "aggregated",
      "source_file": "helm_lite_aggregated.parquet",
      "parquet_filter": "legalbench",
      "models": 91,
      "items": 2142
    },
    "MATH Competition": {
      "source_type": "aggregated",
      "source_file": "helm_lite_aggregated.parquet",
      "parquet_filter": "mathscenario",
      "models": 91,
      "items": 1303
    },
    "MMLU": {
      "source_type": "tinybenchmarks",
      "source_file": "mmlu_fields.pickle",
      "pickle_keys": null,
      "pickle_key_pattern": "hendrycksTest",
      "models": 428,
      "items": 28084
    },
    "MedQA": {
      "source_type": "aggregated",
      "source_file": "helm_lite_aggregated.parquet",
      "parquet_filter": "medqascenario",
      "models": 91,
      "items": 1000
    },
    "NarrativeQA": {
      "source_type": "aggregated",
      "source_file": "helm_lite_aggregated.parquet",
      "parquet_filter": "narrativeqascenario",
      "models": 91,
      "items": 940
    },
    "NaturalQA": {
      "source_type": "aggregated",
      "source_file": "helm_lite_aggregated.parquet",
      "parquet_filter": "naturalqascenario",
      "models": 91,
      "items": 2000
    },
    "OpenBookQA": {
      "source_type": "aggregated",
      "source_file": "helm_lite_aggregated.parquet",
      "parquet_filter": "openbookqa",
      "models": 91,
      "items": 500
    },
    "TruthfulQA": {
      "source_type": "tinybenchmarks",
      "source_file": "lb.pickle",
      "pickle_keys": ["harness_truthfulqa_mc_0"],
      "models": 395,
      "items": 857
    },
    "WMT-14 Translation": {
      "source_type": "aggregated",
      "source_file": "helm_lite_aggregated.parquet",
      "parquet_filter": "wmt14scenario",
      "models": 91,
      "items": 5000
    },
    "Winogrande": {
      "source_type": "tinybenchmarks",
      "source_file": "lb.pickle",
      "pickle_keys": ["harness_winogrande_5"],
      "models": 395,
      "items": 1307
    }
  },
  
  "paths": {
    "_note": "Paths are relative to project root. Use load_data_source_config() which resolves them.",
    "tinybenchmarks_dir": "aggregated_data/tinybenchmarks",
    "aggregated_dir": "aggregated_data/aggregated"
  }
}




